{"lichAm": "27/05/2020 (Canh Tý)", "NgayRam": 18, "MungMot": 4, "TetNguyenDan": 210, "TetNguyentieu": 224, "TetHanthuc": 271, "GiotoHungVuong": 278, "LePhatDan": 313, "TetDoanngo": 332, "LeVuLan": 47, "TetTrungthu": 76, "Ongtaochautroi": 202, "TetDuonglich": 168, "HocsinhSinhvien": 176, "ThanhlapDang": 201, "ThaythuocVN": 225, "QuoctePhunu": 234, "ThanhlapDoan": 252, "SachVN": 278, "Giaiphong": 287, "QuocteLaodong": 288, "ThanhlapDoi": 302, "NgaysinhBacHo": 306, "QuocteThieunhi": 319, "ThuongbinhLietsi": 10, "CachmangThang8": 33, "Quockhanh": 47, "DoanhnhanVN": 88, "PhunuVN": 95, "NhagiaoVN": 126, "QuandoiVN": 158, "Giangsinh": 160, "author": "exlab247@gmail.com"}